AndroidQQ/Android.py
AndroidQQ/Tcp.py
AndroidQQ/__init__.py
AndroidQQ/Echo/Tcp.py
AndroidQQ/Echo/__init__.py
AndroidQQ/http/ClientKey.py
AndroidQQ/http/__init__.py
AndroidQQ/http/accounts.py
AndroidQQ/http/friends.py
AndroidQQ/http/game_credit.py
AndroidQQ/http/headers.py
AndroidQQ/http/level.py
AndroidQQ/http/music.py
AndroidQQ/http/qqsignin.py
AndroidQQ/http/weishi.py
AndroidQQ/im/__init__.py
AndroidQQ/im/oidb/__init__.py
AndroidQQ/im/oidb/OidbSvc_0xc96/OidbSvc_0xc96_pb2.py
AndroidQQ/im/oidb/OidbSvc_0xc96/__init__.py
AndroidQQ/im/oidb/cmd0x88d/__init__.py
AndroidQQ/im/oidb/cmd0x88d/oidb_0x88d_pb2.py
AndroidQQ/im/oidb/cmd0x922/PushInfo_pb2.py
AndroidQQ/im/oidb/cmd0x922/__init__.py
AndroidQQ/im/oidb/cmd0x922/cmd0x922_pb2.py
AndroidQQ/im/oidb/cmd0xeb8/__init__.py
AndroidQQ/im/oidb/cmd0xeb8/cmd0xeb8_pb2.py
AndroidQQ/im/oidb/oidb_0xc05/__init__.py
AndroidQQ/im/oidb/oidb_0xc05/oidb_0xc05_pb2.py
AndroidQQ/im/oidb/oidb_sso/__init__.py
AndroidQQ/im/oidb/oidb_sso/oidb_sso_pb2.py
AndroidQQ/im/oidb/qqconnect/__init__.py
AndroidQQ/im/oidb/qqconnect/qqconnect_pb2.py
AndroidQQ/im/oidb/scanlogin/__init__.py
AndroidQQ/im/oidb/scanlogin/scanlogin_pb2.py
AndroidQQ/log/__init__.py
AndroidQQ/pack/Heartbeat_Alive.py
AndroidQQ/pack/MQUpdateSvc_com_qq_ti_web_scanlogin.py
AndroidQQ/pack/MQUpdateSvc_com_qq_vip_zb_web_OidbSvc_0xdfa_0.py
AndroidQQ/pack/OidbSvc_0x88d_1.py
AndroidQQ/pack/OidbSvc_0xc05.py
AndroidQQ/pack/OidbSvc_0xc96.py
AndroidQQ/pack/OidbSvc_0xeb8.py
AndroidQQ/pack/StatSvc_register.py
AndroidQQ/pack/__init__.py
AndroidQQ/pack/friendlist.py
AndroidQQ/pack/trpc_metaverse_mob_proxy_svr_MobProxy_SsoHandle.py
AndroidQQ/pack/SQQzoneSvc/__init__.py
AndroidQQ/pack/SQQzoneSvc/delUgc.py
AndroidQQ/pack/SQQzoneSvc/like.py
AndroidQQ/pack/SQQzoneSvc/publishmood.py
AndroidQQ/pack/SQQzoneSvc/shuoshuo.py
AndroidQQ/pack/SummaryCard/ReqSummaryCard.py
AndroidQQ/pack/SummaryCard/__init__.py
AndroidQQ/proto/IM_r_pb2.py
AndroidQQ/proto/__init__.py
AndroidQQ/proto/wtlogin_pb2.py
AndN-0.6.4.dist-info/METADATA
AndN-0.6.4.dist-info/WHEEL
AndN-0.6.4.dist-info/top_level.txt
AndN-0.6.4.dist-info/RECORD
