Metadata-Version: 2.1
Name: AndN
Version: 0.6.4
Home-page: https://github.com/grayrail000/AndroidQQ
Author: 1a
Author-email: 
Requires-Dist: AndroidTools
Requires-Dist: protobuf (==4.23.4)
Requires-Dist: cryptography
Requires-Dist: bs4
Requires-Dist: urllib3 (==1.26.16)
Requires-Dist: pydantic
Requires-Dist: requests
Requires-Dist: python-box
Requires-Dist: PySocks
